Metadata-Version: 2.1
Name: odoo-addon-fastapi_auth_api_key
Version: 18.0.1.0.0.4
Requires-Python: >=3.10
Requires-Dist: odoo-addon-auth_api_key_group==18.0.*
Requires-Dist: odoo-addon-fastapi==18.0.*
Requires-Dist: odoo==18.0.*
Summary: Fastapi Auth API Key
Home-page: https://github.com/OCA/rest-framework
License: AGPL-3
Author: Camptocamp, Odoo Community Association (OCA)
Author-email: support@odoo-community.org
Classifier: Programming Language :: Python
Classifier: Framework :: Odoo
Classifier: Framework :: Odoo :: 18.0
Classifier: License :: OSI Approved :: GNU Affero General Public License v3
